odoo9_addon_product_warranty-9.0.1.0.0.99.dev6-py3.8-nspkg.pth
odoo_addons/product_warranty/README.rst
odoo_addons/product_warranty/__init__.py
odoo_addons/product_warranty/__openerp__.py
odoo_addons/product_warranty/demo/product_warranty.xml
odoo_addons/product_warranty/demo/res_company.xml
odoo_addons/product_warranty/i18n/de.po
odoo_addons/product_warranty/i18n/es.po
odoo_addons/product_warranty/i18n/es_MX.po
odoo_addons/product_warranty/i18n/es_PA.po
odoo_addons/product_warranty/i18n/es_VE.po
odoo_addons/product_warranty/i18n/fr.po
odoo_addons/product_warranty/i18n/product_warranty.pot
odoo_addons/product_warranty/i18n/pt_BR.po
odoo_addons/product_warranty/i18n/ro.po
odoo_addons/product_warranty/i18n/sl.po
odoo_addons/product_warranty/images/product_warranty.png
odoo_addons/product_warranty/models/__init__.py
odoo_addons/product_warranty/models/product_supplierinfo.py
odoo_addons/product_warranty/models/res_company.py
odoo_addons/product_warranty/models/return_instruction.py
odoo_addons/product_warranty/security/ir.model.access.csv
odoo_addons/product_warranty/static/description/icon.png
odoo_addons/product_warranty/tests/__init__.py
odoo_addons/product_warranty/tests/test_product_warranty.py
odoo_addons/product_warranty/views/product_warranty.xml
odoo_addons/product_warranty/views/res_company.xml
odoo9_addon_product_warranty-9.0.1.0.0.99.dev6.dist-info/METADATA
odoo9_addon_product_warranty-9.0.1.0.0.99.dev6.dist-info/WHEEL
odoo9_addon_product_warranty-9.0.1.0.0.99.dev6.dist-info/namespace_packages.txt
odoo9_addon_product_warranty-9.0.1.0.0.99.dev6.dist-info/top_level.txt
odoo9_addon_product_warranty-9.0.1.0.0.99.dev6.dist-info/RECORD
